<property name="izpack.dir" value="${basedir}/lib/IzPack"/>
<property name="version" value="1" />
<property name="revision" value="1" />
<target name="help">
    <echo message="Please run: $ ant -v -projecthelp"/>
</target>
<target name="release" description="Erstellt eine tagesaktuelle JAR-Datei" depends="build">
	<tstamp />
    <jar destfile="dist/kafbas.jar" >
		<manifest>
			<attribute name="Build-By" value="Erik Wegner"/>
			<attribute name="Main-class" value="de.ewus.kafbas.Kafbas"/>
		</manifest>
		<fileset dir="bin">
			<include name="**"/>
		</fileset>
		<fileset dir="${basedir}/ressourcen">
			<include name="appicon.png"/>
		</fileset>
	</jar>
</target>
<target name="runrelease" description="Führe die Release-Jar-Datei aus" depends="release">
  <java classname="de.ewus.kafbas.Kafbas" fork="true">
    <classpath refid="project.classpath"/>
    <classpath>
      <pathelement location="dist/kafbas.jar" />
    </classpath>
  </java>
</target>
<taskdef name="izpack" classpath="${izpack.dir}/compiler.jar" classname="com.izforge.izpack.ant.IzPackTask" />
<target name="installer" description="Erstelle einen Installer" depends="release">
	<buildnumber />
	<echo message="Build-Number: ${build.number}" />
    	<delete>
    		<fileset file="dist/kafbas-installer-*.jar" />
    		<fileset file="dist/kafbas-*.jar" />
    		<fileset file="dist/handbuch-*.pdf" />
    	</delete>
	<izpack input="kafbas-install.xml"
		output="dist/kafbas-installer.jar"
		installerType="standard" basedir="${basedir}"
		izPackDir="${izpack.dir}" />
	<copy file="dist/kafbas-installer.jar" tofile="dist/kafbas-installer-${version}.${revision}.${build.number}.jar" />
	<copy file="dist/kafbas.jar" tofile="dist/kafbas-${version}.${revision}.${build.number}.jar" />
 	<copy file="ressourcen/handbuch/handbuch.pdf" tofile="dist/handbuch-${version}.${revision}.${build.number}.pdf" />
</target>
